Metadata-Version: 1.1
Name: django-eztables
Version: 0.3.0
Summary: jQuery Datatables integration for Django
Home-page: https://github.com/noirbizarre/django-eztables
Author: Axel Haustant
Author-email: noirbizarre+django@gmail.com
License: LGPL
Download-URL: http://pypi.python.org/pypi/django-eztables
Platform: UNKNOWN
Classifier: Framework :: Django
Classifier: Development Status :: 4 - Beta
Classifier: Programming Language :: Python
Classifier: Programming Language :: Python :: 3
Classifier: Environment :: Web Environment
Classifier: Operating System :: OS Independent
Classifier: Intended Audience :: Developers
Classifier: Topic :: System :: Software Distribution
Classifier: Programming Language :: Python
Classifier: Topic :: Software Development :: Libraries :: Python Modules
Classifier: License :: OSI Approved :: GNU Library or Lesser General Public License (LGPL)
